nc_gcode_interpreter-0.1.12.dist-info/METADATA
nc_gcode_interpreter-0.1.12.dist-info/WHEEL
nc_gcode_interpreter-0.1.12.dist-info/licenses/LICENSE
nc_gcode_interpreter/__init__.py
nc_gcode_interpreter/_internal.cpython-312-x86_64-linux-gnu.so
nc_gcode_interpreter/_internal.pyi
nc_gcode_interpreter/ggroups.json
nc_gcode_interpreter/py.typed
nc_gcode_interpreter-0.1.12.dist-info/RECORD
