Metadata-Version: 2.4
Name: nc-gcode-interpreter
Version: 0.1.12
Classifier: Programming Language :: Rust
Classifier: Programming Language :: Python :: Implementation :: CPython
Classifier: Programming Language :: Python :: 3.12
Classifier: Programming Language :: Python :: 3.13
Classifier: License :: OSI Approved :: MIT License
Classifier: Operating System :: OS Independent
Classifier: Topic :: Software Development :: Libraries :: Python Modules
Requires-Dist: maturin>=1.7.4
Requires-Dist: polars[pyarrow]>=1.9.0
Requires-Dist: jupyter>=1.1.1 ; extra == 'dev'
Requires-Dist: pytest>=8.3.3 ; extra == 'test'
Requires-Dist: mypy ; extra == 'test'
Provides-Extra: dev
Provides-Extra: test
License-File: LICENSE
Summary: A interpreter for NC (Numerical Control) GCode
Author-email: CEAD Group <software@ceadgroup.com>
Requires-Python: >=3.12
Project-URL: Homepage, https://github.com/CEAD-group/nc-gcode-interpreter
Project-URL: Repository, https://github.com/CEAD-group/nc-gcode-interpreter.git
Project-URL: Documentation, https://github.com/CEAD-group/nc-gcode-interpreter/blob/main/README.md
